pullenti/Sdk.py
pullenti/__init__.py
pullenti/morph/CharsInfo.py
pullenti/morph/LanguageHelper.py
pullenti/morph/MorphAspect.py
pullenti/morph/MorphBaseInfo.py
pullenti/morph/MorphCase.py
pullenti/morph/MorphClass.py
pullenti/morph/MorphFinite.py
pullenti/morph/MorphForm.py
pullenti/morph/MorphGender.py
pullenti/morph/MorphLang.py
pullenti/morph/MorphMiscInfo.py
pullenti/morph/MorphMood.py
pullenti/morph/MorphNumber.py
pullenti/morph/MorphPerson.py
pullenti/morph/MorphTense.py
pullenti/morph/MorphToken.py
pullenti/morph/MorphVoice.py
pullenti/morph/MorphWordForm.py
pullenti/morph/MorphologyService.py
pullenti/morph/__init__.py
pullenti/morph/internal/ByteArrayWrapper.py
pullenti/morph/internal/InnerMorphology.py
pullenti/morph/internal/MorphDeserializer.py
pullenti/morph/internal/MorphEngine.py
pullenti/morph/internal/MorphRule.py
pullenti/morph/internal/MorphRuleVariant.py
pullenti/morph/internal/MorphRuleVariantRef.py
pullenti/morph/internal/MorphTreeNode.py
pullenti/morph/internal/TextWrapper.py
pullenti/morph/internal/UniLexWrap.py
pullenti/morph/internal/UnicodeInfo.py
pullenti/morph/internal/__init__.py
pullenti/morph/internal/properties/__init__.py
pullenti/morph/internal/properties/m_en.dat
pullenti/morph/internal/properties/m_ru.dat
pullenti/morph/internal/properties/m_ua.dat
pullenti/ner/AnalysisResult.py
pullenti/ner/Analyzer.py
pullenti/ner/ExtOntology.py
pullenti/ner/ExtOntologyItem.py
pullenti/ner/MetaToken.py
pullenti/ner/MorphCollection.py
pullenti/ner/NumberSpellingType.py
pullenti/ner/NumberToken.py
pullenti/ner/Processor.py
pullenti/ner/ProcessorService.py
pullenti/ner/ProxyReferent.py
pullenti/ner/Referent.py
pullenti/ner/ReferentToken.py
pullenti/ner/Slot.py
pullenti/ner/SourceOfAnalysis.py
pullenti/ner/TextAnnotation.py
pullenti/ner/TextToken.py
pullenti/ner/Token.py
pullenti/ner/__init__.py
pullenti/ner/address/AddressAnalyzer.py
pullenti/ner/address/AddressBuildingType.py
pullenti/ner/address/AddressDetailType.py
pullenti-4.1.dist-info/METADATA
pullenti-4.1.dist-info/WHEEL
pullenti-4.1.dist-info/top_level.txt
pullenti-4.1.dist-info/RECORD
